XOTweet/__init__.py
XOTweet/__version__.py
XOTweet/input.py
XOTweet/xo_tweet.py
XOTweet/core/__init__.py
XOTweet/core/exceptions.py
XOTweet/core/parser.py
XOTweet/core/scrap.py
XOTweet/core/settings.py
XOTweet/core/user_agents.py
XOTweet/core/utils.py
XOTweet/core/workers.py
XOTweet-1.1.0.dist-info/LICENSE
XOTweet-1.1.0.dist-info/METADATA
XOTweet-1.1.0.dist-info/WHEEL
XOTweet-1.1.0.dist-info/entry_points.txt
XOTweet-1.1.0.dist-info/top_level.txt
XOTweet-1.1.0.dist-info/RECORD
