Metadata-Version: 2.1
Name: XOTweet
Version: 1.1.0
Summary: XOTweet is a tweet bot that scraps twitter for keywords and returns all valid tweets
Home-page: https://strobes.co/
Author: Akhil Reni
Author-email: akhil@wesecureapp.com
License: GPLv3
Platform: UNKNOWN
Requires-Python: >=3.6
Requires-Dist: python-dateutil (==2.8.1)
Requires-Dist: requests (==2.24.0)
